MANIFEST.in
README.md
requirements.txt
setup.py
datascope/__init__.py
datascope/experiments/__init__.py
datascope/experiments/__main__.py
datascope/experiments/version.py
datascope/experiments/baselines/__init__.py
datascope/experiments/baselines/influence/__init__.py
datascope/experiments/baselines/influence/dataset.py
datascope/experiments/baselines/influence/genericNeuralNet.py
datascope/experiments/baselines/influence/hessians.py
datascope/experiments/baselines/influence/importance.py
datascope/experiments/baselines/influence/logisticRegressionWithLBFGS.py
datascope/experiments/baselines/matchingnet/__init__.py
datascope/experiments/baselines/matchingnet/default_configs.py
datascope/experiments/baselines/matchingnet/few_shot_classifier.py
datascope/experiments/baselines/matchingnet/matchingnet_networks.py
datascope/experiments/baselines/matchingnet/predesigned_modules.py
datascope/experiments/baselines/matchingnet/resnet.py
datascope/experiments/baselines/matchingnet/utils.py
datascope/experiments/bench/__init__.py
datascope/experiments/bench/base.py
datascope/experiments/bench/commands.py
datascope/experiments/bench/generator.py
datascope/experiments/bench/main.py
datascope/experiments/datasets/__init__.py
datascope/experiments/datasets/base.py
datascope/experiments/datasets/cache.py
datascope/experiments/pipelines/__init__.py
datascope/experiments/pipelines/models.py
datascope/experiments/pipelines/pipelines.py
datascope/experiments/pipelines/postprocessors.py
datascope/experiments/pipelines/utility.py
datascope/experiments/reports/__init__.py
datascope/experiments/reports/aggregate_plot.py
datascope/experiments/scenarios/__init__.py
datascope/experiments/scenarios/compute_time.py
datascope/experiments/scenarios/data_discard.py
datascope/experiments/scenarios/data_repair_scenario.py
datascope/experiments/scenarios/label_repair.py
datascope/experiments/scenarios/marginal_contribution.py
datascope/experiments/utility/__init__.py
datascope_experiments.egg-info/PKG-INFO
datascope_experiments.egg-info/SOURCES.txt
datascope_experiments.egg-info/dependency_links.txt
datascope_experiments.egg-info/entry_points.txt
datascope_experiments.egg-info/requires.txt
datascope_experiments.egg-info/top_level.txt