Metadata-Version: 2.1
Name: datascope-experiments
Version: 0.0.98
Summary: Module for running experiments on top of datascope.
Home-page: https://ease.ml/datascope/
Author-email: easeml@ds3lab.com
License: MIT
Platform: UNKNOWN
